[{"timestamp":"2023-11-01T16:31:05.629Z","count":0,"uniques":0},{"timestamp":"2023-12-01T16:31:05.629Z","count":0,"uniques":0},{"timestamp":"2024-01-01T16:31:05.629Z","count":0,"uniques":0},{"timestamp":"2024-02-01T16:31:05.629Z","count":0,"uniques":0},{"timestamp":"2024-03-01T16:31:05.629Z","count":0,"uniques":0},{"timestamp":"2024-04-01T16:31:05.629Z","count":0,"uniques":0},{"timestamp":"2024-05-01T16:31:05.629Z","count":0,"uniques":0},{"timestamp":"2024-06-01T12:18:46.790Z","count":75,"uniques":6},{"timestamp":"2024-07-01T18:09:23.610Z","count":10,"uniques":6},{"timestamp":"2024-08-01T06:09:22.422Z","count":3,"uniques":3},{"timestamp":"2024-09-01T18:07:46.012Z","count":4,"uniques":2},{"timestamp":"2024-10-01T18:09:11.741Z","count":7,"uniques":4},{"timestamp":"2024-11-01T00:24:52.336Z","count":5,"uniques":4}]
