[{"timestamp":"2022-04-01T05:35:45.288Z","count":0,"uniques":0},{"timestamp":"2022-05-01T05:35:45.288Z","count":0,"uniques":0},{"timestamp":"2022-06-01T05:35:45.288Z","count":0,"uniques":0},{"timestamp":"2022-07-01T05:35:45.288Z","count":0,"uniques":0},{"timestamp":"2022-08-01T05:35:45.288Z","count":0,"uniques":0},{"timestamp":"2022-09-01T05:35:45.288Z","count":0,"uniques":0},{"timestamp":"2022-10-01T05:35:45.288Z","count":0,"uniques":0},{"timestamp":"2022-11-01T05:35:45.288Z","count":0,"uniques":0},{"timestamp":"2022-12-01T05:35:45.288Z","count":0,"uniques":0},{"timestamp":"2023-01-01T12:37:17.015Z","count":4,"uniques":4},{"timestamp":"2023-02-01T12:43:44.940Z","count":8,"uniques":6},{"timestamp":"2023-03-01T12:36:39.920Z","count":26,"uniques":3},{"timestamp":"2023-04-01T01:39:24.284Z","count":0,"uniques":0}]
